<?xml version="1.0" encoding="UTF-8" ?>
<resources>

  <Content>
    <Name>පන්සිල් මළුව 103 </Name>
    <Url>https://www.youtube.com/embed/pF9NkE7Vi3E</Url>
  </Content>
  <Content>
    <Name>පන්සිල් මළුව 102 </Name>
    <Url>https://www.youtube.com/embed/FvuT-jH-vLQ</Url>
  </Content>
  <Content>
    <Name>පන්සිල් මළුව 101 </Name>
    <Url>https://www.youtube.com/embed/j-Kz_sc30Yg</Url>
  </Content>
  <Content>
    <Name>පන්සිල් මළුව 99 </Name>
    <Url>https://www.youtube.com/embed/3xJGc_nUgZI</Url>
  </Content>
  <Content>
    <Name>පන්සිල් මළුව 98 </Name>
    <Url>https://www.youtube.com/embed/4yyeP7IcRE4</Url>
  </Content>
  <Content>
    <Name>පන්සිල් මළුව 97 </Name>
    <Url>https://www.youtube.com/embed/f-5A3cyEsQo</Url>
  </Content>
  <Content>
    <Name>පන්සිල් මළුව 96 </Name>
    <Url>https://www.youtube.com/embed/C91Htwt0Ps8</Url>
  </Content>
  <Content>
    <Name>පන්සිල් මළුව 95 </Name>
    <Url>https://www.youtube.com/embed/uSdfaA-38K8</Url>
  </Content>
  <Content>
    <Name>පන්සිල් මළුව 94 </Name>
    <Url>https://www.youtube.com/embed/Ev-noB681o4</Url>
  </Content>
  <Content>
    <Name>පන්සිල් මළුව 93 </Name>
    <Url>https://www.youtube.com/embed/QyFlFkVNBKg</Url>
  </Content>
  <Content>
    <Name>පන්සිල් මළුව 92 </Name>
    <Url>https://www.youtube.com/embed/aHsXQlhjpeE</Url>
  </Content>
  <Content>
    <Name>පන්සිල් මළුව 91 </Name>
    <Url>https://www.youtube.com/embed/uRmFXe81gJc</Url>
  </Content>
  <Content>
    <Name>පන්සිල් මළුව 90 </Name>
    <Url>https://www.youtube.com/embed/EK6zR2alz_U</Url>
  </Content>
  <Content>
    <Name>පන්සිල් මළුව 89 </Name>
    <Url>https://www.youtube.com/embed/6MNtnqO7p-Q</Url>
  </Content>
  <Content>
    <Name>පන්සිල් මළුව 88 </Name>
    <Url>https://www.youtube.com/embed/3R8BCZ5x7cI</Url>
  </Content>
  <Content>
    <Name>පන්සිල් මළුව 87 </Name>
    <Url>https://www.youtube.com/embed/-INXVFA4mrg</Url>
  </Content>
  <Content>
    <Name>පන්සිල් මළුව 86 </Name>
    <Url>https://www.youtube.com/embed/Gu8Vf2tD93Y</Url>
  </Content>
  <Content>
    <Name>පන්සිල් මළුව 85 </Name>
    <Url>https://www.youtube.com/embed/OWLiwspM6tY</Url>
  </Content>
  <Content>
    <Name>පන්සිල් මළුව 84 </Name>
    <Url>https://www.youtube.com/embed/iOIB2eejY7Q</Url>
  </Content>
  <Content>
    <Name>පන්සිල් මළුව 83 </Name>
    <Url>https://www.youtube.com/embed/LBk2DB5q1Mo</Url>
  </Content>
  <Content>
    <Name>පන්සිල් මළුව 82 </Name>
    <Url>https://www.youtube.com/embed/5t-dn9_6T9g</Url>
  </Content>
  <Content>
    <Name>පන්සිල් මළුව 81 </Name>
    <Url>https://www.youtube.com/embed/62RgXvfRMwc</Url>
  </Content>
  <Content>
    <Name>පන්සිල් මළුව 80 </Name>
    <Url>https://www.youtube.com/embed/RkhTkQ13Ix4</Url>
  </Content>
  <Content>
    <Name>පන්සිල් මළුව 79 </Name>
    <Url>https://www.youtube.com/embed/7qYW5t9Egjc</Url>
  </Content>
  <Content>
    <Name>පන්සිල් මළුව 78 </Name>
    <Url>https://www.youtube.com/embed/knmhQ70eK04</Url>
  </Content>
  <Content>
    <Name>පන්සිල් මළුව 77 </Name>
    <Url>https://www.youtube.com/embed/mjoU-QWEZ0I</Url>
  </Content>
  <Content>
    <Name>පන්සිල් මළුව 76 </Name>
    <Url>https://www.youtube.com/embed/10W80qeF1Zw</Url>
  </Content>
  <Content>
    <Name>පන්සිල් මළුව 75 </Name>
    <Url>https://www.youtube.com/embed/gJOLqy57_Gk</Url>
  </Content>
  <Content>
    <Name>පන්සිල් මළුව 54 </Name>
    <Url>https://www.youtube.com/embed/6Z7hS43brMM</Url>
  </Content>
  <Content>
    <Name>පන්සිල් මළුව 53 </Name>
    <Url>https://www.youtube.com/embed/Ve5f9Sws6S8</Url>
  </Content>
  <Content>
    <Name>පන්සිල් මළුව 66 </Name>
    <Url>https://www.youtube.com/embed/d5YomDH13Zg</Url>
  </Content>
  <Content>
    <Name>පන්සිල් මළුව 74 </Name>
    <Url>https://www.youtube.com/embed/F_ZOpjG44LI</Url>
  </Content>
  <Content>
    <Name>පන්සිල් මළුව 73 </Name>
    <Url>https://www.youtube.com/embed/eNCf1se_5ww</Url>
  </Content>
  <Content>
    <Name>පන්සිල් මළුව 72 </Name>
    <Url>https://www.youtube.com/embed/7uhZtVuw2NU</Url>
  </Content>
  <Content>
    <Name>පන්සිල් මළුව 71 </Name>
    <Url>https://www.youtube.com/embed/5T2fEl2d_-4</Url>
  </Content>
  <Content>
    <Name>පන්සිල් මළුව 70 </Name>
    <Url>https://www.youtube.com/embed/Cl0aluzZx5k</Url>
  </Content>
  <Content>
    <Name>පන්සිල් මළුව 69 </Name>
    <Url>https://www.youtube.com/embed/KbCy02AhTms</Url>
  </Content>
  <Content>
    <Name>පන්සිල් මළුව 68 </Name>
    <Url>https://www.youtube.com/embed/a39HPZw6IOc</Url>
  </Content>
  <Content>
    <Name>පන්සිල් මළුව 67 </Name>
    <Url>https://www.youtube.com/embed/6mKakU7p4mI</Url>
  </Content>
  <Content>
    <Name>පන්සිල් මළුව 65 </Name>
    <Url>https://www.youtube.com/embed/TVxPZWldY5w</Url>
  </Content>
  <Content>
    <Name>පන්සිල් මළුව 64 </Name>
    <Url>https://www.youtube.com/embed/wBSKBuZQTkA</Url>
  </Content>
  <Content>
    <Name>පන්සිල් මළුව 63 </Name>
    <Url>https://www.youtube.com/embed/plbwh8sH-wE</Url>
  </Content>
  <Content>
    <Name>පන්සිල් මළුව 62 </Name>
    <Url>https://www.youtube.com/embed/XJy0GYuUUNk</Url>
  </Content>
  <Content>
    <Name>පන්සිල් මළුව 61 </Name>
    <Url>https://www.youtube.com/embed/SkVxZ8IqbyY</Url>
  </Content>
  <Content>
    <Name>පන්සිල් මළුව 60 </Name>
    <Url>https://www.youtube.com/embed/wtoxE8_7Pjo</Url>
  </Content>
  <Content>
    <Name>පන්සිල් මළුව 59 </Name>
    <Url>https://www.youtube.com/embed/G8wR-8m82cs</Url>
  </Content>
  <Content>
    <Name>පන්සිල් මළුව 58 </Name>
    <Url>https://www.youtube.com/embed/j4E9BAfYZP4</Url>
  </Content>
  <Content>
    <Name>පන්සිල් මළුව 57 </Name>
    <Url>https://www.youtube.com/embed/P9HvXAJN5EA</Url>
  </Content>
  <Content>
    <Name>පන්සිල් මළුව 56 </Name>
    <Url>https://www.youtube.com/embed/uIdUL6Jyd7Y</Url>
  </Content>
  <Content>
    <Name>පන්සිල් මළුව 55 </Name>
    <Url>https://www.youtube.com/embed/POYS2qJmh_s</Url>
  </Content>
  <Content>
    <Name>පන්සිල් මළුව 52 </Name>
    <Url>https://www.youtube.com/embed/YhPjOMGwZmk</Url>
  </Content>
  <Content>
    <Name>පන්සිල් මළුව 51 </Name>
    <Url>https://www.youtube.com/embed/slS7Nl51808</Url>
  </Content>
  <Content>
    <Name>පන්සිල් මළුව 50 </Name>
    <Url>https://www.youtube.com/embed/B3CrtHUnqQo</Url>
  </Content>
  <Content>
    <Name>පන්සිල් මළුව 49 </Name>
    <Url>https://www.youtube.com/embed/0OSldn5xTlA</Url>
  </Content>
  <Content>
    <Name>පන්සිල් මළුව 48 </Name>
    <Url>https://www.youtube.com/embed/xmgE9ltlbz0</Url>
  </Content>
  <Content>
    <Name>පන්සිල් මළුව 47 </Name>
    <Url>https://www.youtube.com/embed/fDojrq0V1uY</Url>
  </Content>
  <Content>
    <Name>පන්සිල් මළුව 46 </Name>
    <Url>https://www.youtube.com/embed/xhzZ7yVk2hQ</Url>
  </Content>
  <Content>
    <Name>පන්සිල් මළුව 45 </Name>
    <Url>https://www.youtube.com/embed/EfBE7CJig04</Url>
  </Content>
  <Content>
    <Name>පන්සිල් මළුව 44 </Name>
    <Url>https://www.youtube.com/embed/tkFvhU-B0ow</Url>
  </Content>
  <Content>
    <Name>පන්සිල් මළුව 43 </Name>
    <Url>https://www.youtube.com/embed/CPBFhKQgdls</Url>
  </Content>
  <Content>
    <Name>පන්සිල් මළුව 42 </Name>
    <Url>https://www.youtube.com/embed/m3GJ6ZY3tdc</Url>
  </Content>
  <Content>
    <Name>පන්සිල් මළුව 41 </Name>
    <Url>https://www.youtube.com/embed/uTiWjlNT2NA</Url>
  </Content>
  <Content>
    <Name>පන්සිල් මළුව 40 </Name>
    <Url>https://www.youtube.com/embed/U4cbHD0YdXA</Url>
  </Content>
  <Content>
    <Name>පන්සිල් මළුව 39 </Name>
    <Url>https://www.youtube.com/embed/MpJdOfuAyiI</Url>
  </Content>
  <Content>
    <Name>පන්සිල් මළුව 38 </Name>
    <Url>https://www.youtube.com/embed/gPsLYnByjX4</Url>
  </Content>
  <Content>
    <Name>පන්සිල් මළුව 37 </Name>
    <Url>https://www.youtube.com/embed/uXjGrYWDZ1I</Url>
  </Content>
  <Content>
    <Name>පන්සිල් මළුව 36 </Name>
    <Url>https://www.youtube.com/embed/F-rL5uBlOTs</Url>
  </Content>
  <Content>
    <Name>පන්සිල් මළුව 35 </Name>
    <Url>https://www.youtube.com/embed/NnpNKXwTz7o</Url>
  </Content>
  <Content>
    <Name>පන්සිල් මළුව 34 </Name>
    <Url>https://www.youtube.com/embed/hkKz-Az5PuQ</Url>
  </Content>
  <Content>
    <Name>පන්සිල් මළුව 33 </Name>
    <Url>https://www.youtube.com/embed/1g2Optlh8ho</Url>
  </Content>
  <Content>
    <Name>පන්සිල් මළුව 32 </Name>
    <Url>https://www.youtube.com/embed/9u7IbyMectE</Url>
  </Content>
  <Content>
    <Name>පන්සිල් මළුව 31 </Name>
    <Url>https://www.youtube.com/embed/YDM2hYa2iIg</Url>
  </Content>
  <Content>
    <Name>පන්සිල් මළුව 30 </Name>
    <Url>https://www.youtube.com/embed/A85EWKk18PM</Url>
  </Content>
  <Content>
    <Name>පන්සිල් මළුව 29 </Name>
    <Url>https://www.youtube.com/embed/HiXlllTUayI</Url>
  </Content>
  <Content>
    <Name>පන්සිල් මළුව 28 </Name>
    <Url>https://www.youtube.com/embed/fK0Z35k3_v0</Url>
  </Content>
  <Content>
    <Name>පන්සිල් මළුව 27 </Name>
    <Url>https://www.youtube.com/embed/AR-cRIiyI3o</Url>
  </Content>
  <Content>
    <Name>පන්සිල් මළුව 26 </Name>
    <Url>https://www.youtube.com/embed/-y0RbPzMFnk</Url>
  </Content>
  <Content>
    <Name>පන්සිල් මළුව 25 </Name>
    <Url>https://www.youtube.com/embed/fFg5duSFOGs</Url>
  </Content>
  <Content>
    <Name>පන්සිල් මළුව 24 </Name>
    <Url>https://www.youtube.com/embed/X4sxk3m2wFA</Url>
  </Content>
  <Content>
    <Name>පන්සිල් මළුව 23 </Name>
    <Url>https://www.youtube.com/embed/VTzTkn9vFUY</Url>
  </Content>
  <Content>
    <Name>පන්සිල් මළුව 22 </Name>
    <Url>https://www.youtube.com/embed/WpePU_oly5o</Url>
  </Content>
  <Content>
    <Name>පන්සිල් මළුව 21 </Name>
    <Url>https://www.youtube.com/embed/FJ9AZBncCSI</Url>
  </Content>
  <Content>
    <Name>පන්සිල් මළුව 12 </Name>
    <Url>https://www.youtube.com/embed/1zM9plyztcM</Url>
  </Content>
  <Content>
    <Name>පන්සිල් මළුව 20 </Name>
    <Url>https://www.youtube.com/embed/JIMJU7l6nVk</Url>
  </Content>
  <Content>
    <Name>පන්සිල් මළුව 19 </Name>
    <Url>https://www.youtube.com/embed/MuQJR7y2PM4</Url>
  </Content>
  <Content>
    <Name>පන්සිල් මළුව 18 </Name>
    <Url>https://www.youtube.com/embed/z0Ty_hAj3wM</Url>
  </Content>
  <Content>
    <Name>පන්සිල් මළුව 17 </Name>
    <Url>https://www.youtube.com/embed/L8HBMmzg6Iw</Url>
  </Content>
  <Content>
    <Name>පන්සිල් මළුව 16 </Name>
    <Url>https://www.youtube.com/embed/MFgsV1hn6h4</Url>
  </Content>
  <Content>
    <Name>පන්සිල් මළුව 15 </Name>
    <Url>https://www.youtube.com/embed/nAJqMLMQONs</Url>
  </Content>
  <Content>
    <Name>පන්සිල් මළුව 14 </Name>
    <Url>https://www.youtube.com/embed/T7Ptq9-he3s</Url>
  </Content>
  <Content>
    <Name>පන්සිල් මළුව 13 </Name>
    <Url>https://www.youtube.com/embed/95hxVrqip7I</Url>
  </Content>
  <Content>
    <Name>පන්සිල් මළුව 11 </Name>
    <Url>https://www.youtube.com/embed/OflEBdkLC-A</Url>
  </Content>
  <Content>
    <Name>පන්සිල් මළුව 10 </Name>
    <Url>https://www.youtube.com/embed/9pG70t-oaEo</Url>
  </Content>
  <Content>
    <Name>පන්සිල් මළුව 09 </Name>
    <Url>https://www.youtube.com/embed/Ni2xIUFsWH4</Url>
  </Content>
  <Content>
    <Name>පන්සිල් මළුව 08 </Name>
    <Url>https://www.youtube.com/embed/W-PRbi_oFW0</Url>
  </Content>
  <Content>
    <Name>පන්සිල් මළුව 07 </Name>
    <Url>https://www.youtube.com/embed/gjC5HASAnxc</Url>
  </Content>
  <Content>
    <Name>පන්සිල් මළුව 06 </Name>
    <Url>https://www.youtube.com/embed/f7k0Bb2q5kw</Url>
  </Content>
  <Content>
    <Name>පන්සිල් මළුව 05 </Name>
    <Url>https://www.youtube.com/embed/GJ4SRIfogGc</Url>
  </Content>
  <Content>
    <Name>පන්සිල් මළුව 04 </Name>
    <Url>https://www.youtube.com/embed/qGDCSO31oQ0</Url>
  </Content>
  <Content>
    <Name>පන්සිල් මළුව 03 </Name>
    <Url>https://www.youtube.com/embed/5P4nOe2pemI</Url>
  </Content>


</resources>